concurrent_utils/__init__.py
concurrent_utils/component.py
concurrent_utils/event_loop_thread.py
concurrent_utils/pipe.py
concurrent_utils/serializers.py
concurrent_utils-0.2.0.dist-info/LICENSE
concurrent_utils-0.2.0.dist-info/METADATA
concurrent_utils-0.2.0.dist-info/WHEEL
concurrent_utils-0.2.0.dist-info/entry_points.txt
concurrent_utils-0.2.0.dist-info/top_level.txt
concurrent_utils-0.2.0.dist-info/RECORD
