Metadata-Version: 2.1
Name: concurrent-utils
Version: 0.2.0
Summary: concurrent-utils
Home-page: https://github.com/SillyFreak/ConcurrentUtils
Author: Clemens Koza
Author-email: koza@pria.at
License: AGPLv3+
Keywords: asyncio concurrency
Platform: UNKNOWN
Classifier: Development Status :: 4 - Beta
Classifier: Intended Audience :: Developers
Classifier: Topic :: Software Development
Classifier: License :: OSI Approved :: GNU Affero General Public License v3 or later (AGPLv3+)
Classifier: Programming Language :: Python :: 3
Classifier: Programming Language :: Python :: 3.7
Provides-Extra: dev
Provides-Extra: zmq
Provides-Extra: msgpack
